simc_support/__init__.py
simc_support/py.typed
simc_support/game_data/Expansion.py
simc_support/game_data/Faction.py
simc_support/game_data/Instance.py
simc_support/game_data/ItemLevel.py
simc_support/game_data/Language.py
simc_support/game_data/Race.py
simc_support/game_data/RaidRole.py
simc_support/game_data/Role.py
simc_support/game_data/Season.py
simc_support/game_data/SimcObject.py
simc_support/game_data/Source.py
simc_support/game_data/Stat.py
simc_support/game_data/Talent.py
simc_support/game_data/Trinket.py
simc_support/game_data/WowClass.py
simc_support/game_data/WowSpec.py
simc_support/game_data/__init__.py
simc_support/game_data/data_files/trinkets.json
simc_support/game_data/data_files/wow_classes.json
simc_support/game_data/data_files/trees/death_knight_blood.json
simc_support/game_data/data_files/trees/death_knight_frost.json
simc_support/game_data/data_files/trees/death_knight_unholy.json
simc_support/game_data/data_files/trees/demon_hunter_havoc.json
simc_support/game_data/data_files/trees/demon_hunter_vengeance.json
simc_support/game_data/data_files/trees/druid_balance.json
simc_support/game_data/data_files/trees/druid_feral.json
simc_support/game_data/data_files/trees/druid_guardian.json
simc_support/game_data/data_files/trees/druid_restoration.json
simc_support/game_data/data_files/trees/evoker_augmentation.json
simc_support/game_data/data_files/trees/evoker_devastation.json
simc_support/game_data/data_files/trees/evoker_preservation.json
simc_support/game_data/data_files/trees/hunter_beast_mastery.json
simc_support/game_data/data_files/trees/hunter_marksmanship.json
simc_support/game_data/data_files/trees/hunter_survival.json
simc_support/game_data/data_files/trees/mage_arcane.json
simc_support/game_data/data_files/trees/mage_fire.json
simc_support/game_data/data_files/trees/mage_frost.json
simc_support/game_data/data_files/trees/monk_brewmaster.json
simc_support/game_data/data_files/trees/monk_mistweaver.json
simc_support-11.2.0.6.dist-info/licenses/LICENSE
simc_support-11.2.0.6.dist-info/METADATA
simc_support-11.2.0.6.dist-info/WHEEL
simc_support-11.2.0.6.dist-info/top_level.txt
simc_support-11.2.0.6.dist-info/RECORD
