Metadata-Version: 2.4
Name: simc_support
Version: 11.2.0.6
Summary: Data to support simulations for World of Warcraft with SimulationCraft.
Home-page: https://github.com/Bloodmallet/simc_support
Author: Bloodmallet(EU)
Author-email: bloodmalleteu@gmail.com
License: GNU GENERAL PUBLIC LICENSE
Project-URL: Bug Tracker, https://github.com/Bloodmallet/simc_support/issues
Classifier: Programming Language :: Python :: 3
Classifier: License :: OSI Approved :: GNU General Public License v3 (GPLv3)
Classifier: Operating System :: OS Independent
Requires-Python: >=3.8
License-File: LICENSE
Dynamic: license-file
